cms_named_menus/__init__.py
cms_named_menus/admin.py
cms_named_menus/apps.py
cms_named_menus/cache.py
cms_named_menus/models.py
cms_named_menus/nodes.py
cms_named_menus/settings.py
cms_named_menus/signals.py
cms_named_menus/migrations/0001_initial.py
cms_named_menus/migrations/0002_auto_20150227_1436.py
cms_named_menus/migrations/0003_auto_20170928_0908.py
cms_named_menus/migrations/0004_cmsnamedmenu_site.py
cms_named_menus/migrations/0005_auto_20181204_1554.py
cms_named_menus/migrations/0006_auto_20190201_1645.py
cms_named_menus/migrations/0007_auto_20190520_1353.py
cms_named_menus/migrations/0008_auto_20200522_2039.py
cms_named_menus/migrations/__init__.py
cms_named_menus/static/cmsnamedmenus/css/admin.css
cms_named_menus/static/cmsnamedmenus/css/admin.min.css
cms_named_menus/static/cmsnamedmenus/ext/jquery-3.3.1.min.js
cms_named_menus/static/cmsnamedmenus/ext/jquery-ui.min.js
cms_named_menus/static/cmsnamedmenus/ext/jquery.nestable.js
cms_named_menus/static/cmsnamedmenus/ext/jquery.nestable.min.css
cms_named_menus/static/cmsnamedmenus/ext/jquery.nestable.min.js
cms_named_menus/templates/cms_named_menus/admin_select.html
cms_named_menus/templates/cms_named_menus/change_form.html
cms_named_menus/templates/cms_named_menus/fieldset.html
cms_named_menus/templates/cms_named_menus/nestable_item.html
cms_named_menus/templatetags/__init__.py
cms_named_menus/templatetags/named_cms_menu_tags.py
djangocms_named_menus-2.0.2.dist-info/LICENSE
djangocms_named_menus-2.0.2.dist-info/METADATA
djangocms_named_menus-2.0.2.dist-info/WHEEL
djangocms_named_menus-2.0.2.dist-info/top_level.txt
djangocms_named_menus-2.0.2.dist-info/RECORD
