Metadata-Version: 2.1
Name: djangocms-named-menus
Version: 2.0.2
Summary: Allows you to add and edit custom named menus similar to Wordpress menus
Home-page: https://github.com/mcldev/djangocms-named-menus
Author: Ryan Bagwell, Rogerio Carrasqueira, Michael Carder Ltd
License: MIT
Classifier: Environment :: Web Environment
Classifier: Intended Audience :: Developers
Classifier: License :: OSI Approved :: MIT License
Classifier: Operating System :: OS Independent
Classifier: Framework :: Django
Classifier: Framework :: Django :: 1.11
Classifier: Framework :: Django :: 2.0
Classifier: Framework :: Django :: 2.1
Classifier: Framework :: Django :: 2.2
Classifier: Programming Language :: Python
Classifier: Programming Language :: Python :: 3.6
Classifier: Programming Language :: Python :: 3.7
Classifier: Programming Language :: Python :: 3.8
Classifier: Topic :: Internet :: WWW/HTTP
Classifier: Topic :: Internet :: WWW/HTTP :: Dynamic Content
License-File: LICENSE
Requires-Dist: Django >=2.2
Requires-Dist: django-classy-tags
Requires-Dist: django-cms >=3.3
Requires-Dist: jsonfield >=1.0.0
Requires-Dist: django-autoslug >=1.7.2
